MANIFEST.in
README.rst
setup.cfg
setup.py
Flask_Flacro.egg-info/PKG-INFO
Flask_Flacro.egg-info/SOURCES.txt
Flask_Flacro.egg-info/dependency_links.txt
Flask_Flacro.egg-info/not-zip-safe
Flask_Flacro.egg-info/requires.txt
Flask_Flacro.egg-info/top_level.txt
flask_flacro/__init__.py
flask_flacro/compat.py
flask_flacro/flacro.py
flask_flacro/packaged_macros.py
flask_flacro/templates/macros/accordian.html
flask_flacro/templates/macros/list.html
flask_flacro/templates/macros/tab.html
tests/__init__.py
tests/__init__.pyc
tests/flacro_test.py
tests/flacro_test.pyc
tests/templates/index.html
tests/templates/test_macros/test.html