Metadata-Version: 1.1
Name: Flask-Flacro
Version: 0.0.8
Summary: flask/jinja2 templating tools
Home-page: https://github.com/thrisp/flacro
Author: hurrata/thrisp
Author-email: blueblank@gmail.com
License: MIT
Platform: any
Classifier: Environment :: Web Environment
Classifier: Intended Audience :: Developers
Classifier: License :: OSI Approved :: BSD License
Classifier: Operating System :: OS Independent
Classifier: Programming Language :: Python
Classifier: Topic :: Internet :: WWW/HTTP :: Dynamic Content
Classifier: Topic :: Software Development :: Libraries :: Python Modules
